pytest_testconfig.py
pytest_testconfig-0.2.0.dist-info/LICENSE
pytest_testconfig-0.2.0.dist-info/METADATA
pytest_testconfig-0.2.0.dist-info/WHEEL
pytest_testconfig-0.2.0.dist-info/entry_points.txt
pytest_testconfig-0.2.0.dist-info/top_level.txt
pytest_testconfig-0.2.0.dist-info/RECORD
