Metadata-Version: 1.2
Name: pytest-testconfig
Version: 0.2.0
Summary: Test configuration plugin for pytest.
Home-page: https://github.com/wojole/pytest-testconfig
Author: Wojciech Olejarz, Bartlomiej Skrobek
Author-email: olejarz.wojciech@gmail.com
Maintainer: Wojciech Olejarz, Bartlomiej Skrobek
Maintainer-email: olejarz.wojciech@gmail.com
License: Apache Software License 2.0
Platform: UNKNOWN
Classifier: Development Status :: 4 - Beta
Classifier: Framework :: Pytest
Classifier: Intended Audience :: Developers
Classifier: Topic :: Software Development :: Testing
Classifier: Programming Language :: Python
Classifier: Programming Language :: Python :: 2.7
Classifier: Programming Language :: Python :: 3
Classifier: Programming Language :: Python :: 3.5
Classifier: Programming Language :: Python :: 3.6
Classifier: Programming Language :: Python :: 3.7
Classifier: Programming Language :: Python :: 3.8
Classifier: Programming Language :: Python :: Implementation :: PyPy
Classifier: Operating System :: OS Independent
Classifier: License :: OSI Approved :: Apache Software License
Requires-Python: >=2.7, !=3.0.*, !=3.1.*, !=3.2.*, !=3.3.*, !=3.4.*
